DjangoQiniu/__init__.py
DjangoQiniu/__init__.pyc
DjangoQiniu/models.py
DjangoQiniu/models.pyc
DjangoQiniu/urls.py
DjangoQiniu/urls.pyc
DjangoQiniu/views.py
DjangoQiniu/views.pyc
DjangoQiniu/widgets.py
DjangoQiniu/widgets.pyc
DjangoQiniu-0.0.1.dist-info/DESCRIPTION.rst
DjangoQiniu-0.0.1.dist-info/METADATA
DjangoQiniu-0.0.1.dist-info/RECORD
DjangoQiniu-0.0.1.dist-info/WHEEL
DjangoQiniu-0.0.1.dist-info/metadata.json
DjangoQiniu-0.0.1.dist-info/top_level.txt
