Metadata-Version: 2.0
Name: DjangoQiniu
Version: 0.0.1
Summary: 在Django后台可以使用Qiniu的插件
Home-page: https://github.com/NunchakusHuang/DjangoQiniu
Author: NunchakusHuang
Author-email: hynever@qq.com
License: UNKNOWN
Download-URL: https://github.com/NunchakusHuang/DjangoQiniu/tarball/2017-05-11
Platform: Windows
Platform: MacOS
Platform: Unix
Classifier: Development Status :: 5 - Production/Stable
Classifier: Intended Audience :: Developers
Classifier: License :: OSI Approved :: BSD License
Classifier: Natural Language :: Chinese (Simplified)
Classifier: Operating System :: Microsoft :: Windows
Classifier: Operating System :: MacOS
Classifier: Operating System :: Unix
Classifier: Programming Language :: Python
Classifier: Programming Language :: Python :: 2.7
Classifier: Programming Language :: Python :: 3.3
Classifier: Programming Language :: Python :: 3.4
Classifier: Programming Language :: Python :: 3.5
